UCMEC_env/__Init__.py
UCMEC_env/envs/MA_UCMEC_env.py
UCMEC_env/envs/SA_UCMEC_env.py
UCMEC_env/envs/__Init__.py
example_pkg_UCMEC-1.0.0.dist-info/LICENSE
example_pkg_UCMEC-1.0.0.dist-info/METADATA
example_pkg_UCMEC-1.0.0.dist-info/WHEEL
example_pkg_UCMEC-1.0.0.dist-info/top_level.txt
example_pkg_UCMEC-1.0.0.dist-info/RECORD
