Metadata-Version: 2.1
Name: example-pkg-UCMEC
Version: 1.0.0
Summary: Reinforcement Learning Environment for User-centric Mobile Edge Computing 
Home-page: https://github.com/qt315/Multi-agent-UCMEC
Author: Langtian Qin
Author-email: qlt315@mail.ustc.edu.com
License: UNKNOWN
Platform: UNKNOWN
Classifier: Intended Audience :: Developers
Classifier: Programming Language :: Python :: 3.4
Classifier: Programming Language :: Python :: 3.5
Classifier: Programming Language :: Python :: 3.6
Classifier: Programming Language :: Python :: 3.7
Requires-Dist: numpy
Requires-Dist: gym (>=0.12)
